setup.py
nmap/__init__.py
nmap/nmap.py
nmap.egg-info/PKG-INFO
nmap.egg-info/SOURCES.txt
nmap.egg-info/dependency_links.txt
nmap.egg-info/top_level.txt